src/__init__.py
src/__main__.py
src/main.py
src/slicer.py
src/slicer2.py
src/slicer_time.py
audio_slicer-1.0.1.dist-info/LICENSE
audio_slicer-1.0.1.dist-info/METADATA
audio_slicer-1.0.1.dist-info/WHEEL
audio_slicer-1.0.1.dist-info/entry_points.txt
audio_slicer-1.0.1.dist-info/top_level.txt
audio_slicer-1.0.1.dist-info/RECORD
