Metadata-Version: 2.1
Name: audio-slicer
Version: 1.0.1
Summary: Automatically segregates audio and cleans up muted parts
Home-page: https://github.com/ai-forks/audio-slicer
Author: leochen
Author-email: markchen0312@gmail.com
License: MIT
License-File: LICENSE
Requires-Dist: numpy
Requires-Dist: librosa
Requires-Dist: soundfile
Requires-Dist: pydub
